README.md
setup.py
KCOJ_api/__init__.py
KCOJ_api/api.py
KCOJ_api.egg-info/PKG-INFO
KCOJ_api.egg-info/SOURCES.txt
KCOJ_api.egg-info/dependency_links.txt
KCOJ_api.egg-info/requires.txt
KCOJ_api.egg-info/top_level.txt