Metadata-Version: 2.1
Name: KCOJ-api
Version: 1.6
Summary: A Python Module for get data from real KCOJ.
Home-page: https://github.com/kcoj/KCOJ_api
Author: pinlin
Author-email: moneycat711@gmail.com
License: MIT License
Platform: all
